{
	"neonPinEPot" : 
	[
	  {
		"sprite" : [{"x" : 6},{"y" : 15},{"w" : 240},{"h" : 31}]
	  },
	  {
		"sprite" : [{"x" : 6},{"y" : 60},{"w" : 240},{"h" : 31}]
	  },
	  {
		"sprite" : [{"x" : 8},{"y" : 104},{"w" : 240},{"h" : 31}]
	  },
	  {
		"sprite" : [{"x" : 10},{"y" : 191},{"w" : 240},{"h" : 31}]
	  },
	  {
		"sprite" : [{"x" : 10},{"y" : 234},{"w" : 240},{"h" : 31}]
	  },
	  {
		"sprite" : [{"x" : 10},{"y" : 277},{"w" : 240},{"h" : 31}]
	  },
	  {
		"sprite" : [{"x" : 8},{"y" : 146},{"w" : 240},{"h" : 32}]
	  }
	],
	"neonBreakfastDiner" : 
	[
	  {
		"sprite" : [{"x" : 264},{"y" : 14},{"w" : 161},{"h" : 44}]
	  },
	  {
		"sprite" : [{"x" : 264},{"y" : 64},{"w" : 161},{"h" : 44}]
	  },
	  {
		"sprite" : [{"x" : 265},{"y" : 117},{"w" : 161},{"h" : 44}]
	  },
	  {
		"sprite" : [{"x" : 265},{"y" : 168},{"w" : 161},{"h" : 44}]
	  },
	  {
		"sprite" : [{"x" : 265},{"y" : 221},{"w" : 161},{"h" : 44}]
	  },
	  {
		"sprite" : [{"x" : 264},{"y" : 272},{"w" : 161},{"h" : 44}]
	  },
	  {
		"sprite" : [{"x" : 263},{"y" : 321},{"w" : 161},{"h" : 44}]
	  }
	],
	"neonLDevo" : 
	[
	  {
		"sprite" : [{"x" : 434},{"y" : 14},{"w" : 92},{"h" : 31}]
	  },
	  {
		"sprite" : [{"x" : 434},{"y" : 55},{"w" : 92},{"h" : 31}]
	  },
	  {
		"sprite" : [{"x" : 435},{"y" : 98},{"w" : 92},{"h" : 31}]
	  },
	  {
		"sprite" : [{"x" : 434},{"y" : 139},{"w" : 92},{"h" : 31}]
	  },
	  {
		"sprite" : [{"x" : 435},{"y" : 181},{"w" : 92},{"h" : 31}]
	  }  
	],
	"neonRachShop" : 
	[
	  {
		"sprite" : [{"x" : 536},{"y" : 14},{"w" : 240},{"h" : 44}]
	  },
	  {
		"sprite" : [{"x" : 536},{"y" : 67},{"w" : 240},{"h" : 44}]
	  },
	  {
		"sprite" : [{"x" : 535},{"y" : 116},{"w" : 240},{"h" : 44}]
	  },
	  {
		"sprite" : [{"x" : 534},{"y" : 163},{"w" : 240},{"h" : 44}]
	  },
	  {
		"sprite" : [{"x" : 534},{"y" : 213},{"w" : 240},{"h" : 44}]
	  },
	  {
		"sprite" : [{"x" : 534},{"y" : 264},{"w" : 240},{"h" : 44}]
	  }
	],
	"neonAbcShop" :
	[
	  {
		"sprite" : [{"x" : 790},{"y" : 15},{"w" : 136},{"h" : 32}]
	  },
	  {
		"sprite" : [{"x" : 791},{"y" : 54},{"w" : 136},{"h" : 32}]
	  },
	  {
		"sprite" : [{"x" : 792},{"y" : 91},{"w" : 136},{"h" : 32}]
	  },
	  {
		"sprite" : [{"x" : 792},{"y" : 127},{"w" : 136},{"h" : 32}]
	  },
	  {
		"sprite" : [{"x" : 793},{"y" : 165},{"w" : 136},{"h" : 32}]
	  },
	  {
		"sprite" : [{"x" : 794},{"y" : 205},{"w" : 136},{"h" : 32}]
	  },
	  {
		"sprite" : [{"x" : 793},{"y" : 243},{"w" : 136},{"h" : 32}]
	  }	  
	],
	"neonCafeRestaurant" :
	[
	  {
		"sprite" : [{"x" : 939},{"y" : 15},{"w" : 48},{"h" : 17}]
	  },
	  {
		"sprite" : [{"x" : 938},{"y" : 37},{"w" : 48},{"h" : 17}]
	  },
	  	  {
		"sprite" : [{"x" : 938},{"y" : 59},{"w" : 48},{"h" : 17}]
	  },
	  	  {
		"sprite" : [{"x" : 938},{"y" : 80},{"w" : 48},{"h" : 17}]
	  },
	  	  {
		"sprite" : [{"x" : 938},{"y" : 126},{"w" : 48},{"h" : 17}]
	  },
	  {
		"sprite" : [{"x" : 937},{"y" : 148},{"w" : 48},{"h" : 17}]
	  }
	],
	"playerIdleRight1" :
	[
		{
		  "sprite" : [{"x" : 22},{"y" : 16},{"w" : 96},{"h" : 63}]
		}
	],
	"playerIdleRight2" :
	[
		{
		  "sprite" : [{"x" : 1027},{"y" : 83},{"w" : 97},{"h" : 63}]
		}
	],
	"playerIdleRight3" :
	[
		{
		  "sprite" : [{"x" : 1157},{"y" : 83},{"w" : 98},{"h" : 63}]
		}	
	],
	"playerIdleLeft1" :
	[
		{
		  "sprite" : [{"x" : 2434},{"y" : 16},{"w" : 84},{"h" : 63}]
		}
	],
	"playerIdleLeft2" :
	[
		{
		  "sprite" : [{"x" : 1429},{"y" : 83},{"w" : 84},{"h" : 63}]
		}
	],
	"playerIdleLeft3" :
	[
		{
		  "sprite" : [{"x" : 1299},{"y" : 83},{"w" : 83},{"h" : 63}]
		}	
	],
	"playerWalkRight" :
	[
		{
		  "sprite" : [{"x" : 20},{"y" : 85},{"w" : 79},{"h" : 64}]
		},
		{
		  "sprite" : [{"x" : 142},{"y" : 84},{"w" : 89},{"h" : 63}]
		},
		{
		  "sprite" : [{"x" : 278},{"y" : 85},{"w" : 78},{"h" : 64}]
		},
		{
		  "sprite" : [{"x" : 409},{"y" : 85},{"w" : 89},{"h" : 63}]
		}
	],
	"playerWalkLeft" :
	[
		{
		  "sprite" : [{"x" : 2436},{"y" : 85},{"w" : 82},{"h" : 64}]
		},
		{
		  "sprite" : [{"x" : 2314},{"y" : 84},{"w" : 89},{"h" : 63}]
		},
		{
		  "sprite" : [{"x" : 2178},{"y" : 85},{"w" : 82},{"h" : 64}]
		},
		{
		  "sprite" : [{"x" : 2047},{"y" : 85},{"w" : 88},{"h" : 63}]
		}
	],
	"playerJumpRight1" :
	[
		{
		  "sprite" : [{"x" : 560},{"y" : 89},{"w" : 78},{"h" : 63}]
		}
	],	
	"playerJumpRight2" :
	[
		{
		  "sprite" : [{"x" : 714},{"y" : 81},{"w" : 84},{"h" : 66}]	
		}
	],
	"playerJumpLeft1" :
	[
		{
		  "sprite" : [{"x" : 1896},{"y" : 89},{"w" : 94},{"h" : 63}]
		}
	],
	"playerJumpLeft2" :
	[
		{
		  "sprite" : [{"x" : 1742},{"y" : 81},{"w" : 92},{"h" : 66}]
		}
	],
	"playerAirKickRight" :
	[
		{
		  "sprite" : [{"x" : 867},{"y" : 84},{"w" : 100},{"h" : 64}]
		}
	],
	"playerAirKickLeft" :
	[
		{
		  "sprite" : [{"x" : 1589},{"y" : 84},{"w" : 87},{"h" : 64}]
		}
	],
	"playerPunchComboRight1" :
	[
		{
		  "sprite" : [{"x" : 146},{"y" : 14},{"w" : 106},{"h" : 63}]
		}
	],
	"playerPunchComboRight2" :
	[
		{
		  "sprite" : [{"x" : 413},{"y" : 11},{"w" : 109},{"h" : 63}]
		}
	],
	"playerPunchComboRight3" :
	[
		{
		  "sprite" : [{"x" : 548},{"y" : 11},{"w" : 118},{"h" : 63}]
		}
	],
	"playerPunchComboLeft1" :
	[
		{
		  "sprite" : [{"x" : 2310},{"y" : 14},{"w" : 92},{"h" : 63}]
		}
	],
	"playerPunchComboLeft2" :
	[
		{
		  "sprite" : [{"x" : 2042},{"y" : 11},{"w" : 105},{"h" : 63}]
		}
	],
	"playerPunchComboLeft3" :
	[
		{
		  "sprite" : [{"x" : 1908},{"y" : 11},{"w" : 89},{"h" : 63}]
		}
	],
	"playerBackPunchRight1" :
	[
		{
		  "sprite" : [{"x" : 1020},{"y" : 10},{"w" : 96},{"h" : 63}]
		}
	],
	"playerBackPunchRight2" :
	[	{
		  "sprite" : [{"x" : 875},{"y" : 11},{"w" : 88},{"h" : 64}]
		}
	],
	"playerBackPunchLeft1" :
	[
		{
		  "sprite" : [{"x" : 1436},{"y" : 10},{"w" : 91},{"h" : 63}]
		}
	],
	"playerBackPunchLeft2" :
	[
		{
		  "sprite" : [{"x" : 1586},{"y" : 11},{"w" : 101},{"h" : 64}]
		}
	],
	"grabRight" :
	[
		{
		  "sprite" : [{"x" : 17},{"y" : 168},{"w" : 93},{"h" : 63}]
		}
	],
	"grabKickHeadRight1" :
	[
		{
		  "sprite" : [{"x" : 137},{"y" : 166},{"w" : 92},{"h" : 64}]
		}
	],
	"grabKickHeadRight2" :
	[
		{
		  "sprite" : [{"x" : 271},{"y" : 161},{"w" : 110},{"h" : 64}]
		},
		{
		  "sprite" : [{"x" : 414},{"y" : 158},{"w" : 85},{"h" : 63 }]
		}
	],
	"grabLeft" :
	[
		{
		  "sprite" : [{"x" : 2439},{"y" : 168},{"w" : 90},{"h" : 63}]
		}
	],
	"grabKickHeadLeft1" :
	[
		{
		  "sprite" : [{"x" : 2318},{"y" : 166},{"w" : 79},{"h" : 64}]
		}
	],
	"grabKickHeadLeft2" :
	[
		{
		  "sprite" : [{"x" : 2185},{"y" : 161},{"w" : 81},{"h" : 64}]
		},
		{
		  "sprite" : [{"x" : 2042},{"y" : 158},{"w" : 97},{"h" :  63}]
		}
	],
	"grabAirSpinRight1" :
	[
		{
		  "sprite" : [{"x" : 885},{"y" : 159},{"w" : 93},{"h" : 70}]
		}
	],
	"grabAirSpinRight2" :	
	[
		{
		  "sprite" : [{"x" : 1039},{"y" : 162 },{"w" : 100},{"h" : 99}]
		}
	],
	"grabAirSpinRight3" :
	[	
		{
		  "sprite" : [{"x" : 1026},{"y" : 283},{"w" : 109},{"h" : 123}]
		}
	],
	"grabAirSpinRight4" :
	[
		{
		  "sprite" : [{"x" : 1385},{"y" : 285},{"w" : 108},{"h" : 123}]
		}
	],
	"grabAirSpinRight5" :
	[	
		{
		  "sprite" : [{"x" : 1377},{"y" : 162 },{"w" : 129},{"h" : 99}]
		}
	],
	"grabAirSpinRight6" :
	[
		{
		  "sprite" : [{"x" : 1531},{"y" : 159},{"w" : 141},{"h" : 70}]
		}
	],
	"grabAirSpinRight7" :
	[
		{
		  "sprite" : [{"x" : 2436},{"y" : 349},{"w" : 92},{"h" : 63}]
		}
	],
	"grabAirSpinFinisherRight1" :
	[
		{
		  "sprite" : [{"x" : 2299},{"y" : 345},{"w" : 98},{"h" : 63}]
		},
		{
		  "sprite" : [{"x" : 2155},{"y" : 345},{"w" : 108},{"h" : 64}]
		},
		{
		  "sprite" : [{"x" : 2003},{"y" : 338},{"w" : 127},{"h" : 63}]
		}	
	],
	"grabAirSpinFinisherRight2" :
	[
		{
		  "sprite" : [{"x" : 1853 },{"y" : 335},{"w" : 131},{"h" : 63}]
		}
	],
	"grabAirSpinFinisherRight3" :
	[
		{
		  "sprite" : [{"x" : 2003},{"y" : 338},{"w" : 127},{"h" : 63}]
		},
		{
		  "sprite" : [{"x" : 2155},{"y" : 345},{"w" : 108},{"h" : 64}]
		}
	],
	
	"grabAirSpinLeft1" :
	[
		{
		  "sprite" : [{"x" : 1571},{"y" : 159},{"w" : 100},{"h" : 72}]
		}
	],
	"grabAirSpinLeft2" :
	[
		{
		  "sprite" : [{"x" : 1417},{"y" : 162 },{"w" : 89},{"h" : 99}]
		}
	],
	"grabAirSpinLeft3" :
	[
		{
		  "sprite" : [{"x" : 1426},{"y" : 285},{"w" : 67},{"h" : 123}]
		}
	],
	"grabAirSpinLeft4" :
	[
		{
		  "sprite" : [{"x" : 1067},{"y" : 283},{"w" : 68},{"h" : 123}]
		}
	],
	"grabAirSpinLeft5" :
	[
		{
		  "sprite" : [{"x" : 1080},{"y" : 162 },{"w" : 59},{"h" : 99}]
		}
	],
	"grabAirSpinLeft6" :
	[
		{
		  "sprite" : [{"x" : 924},{"y" : 159},{"w" : 54},{"h" : 70}]
		}
	],
	"grabAirSpinLeft7" :
	[
		{
		  "sprite" : [{"x" : 20},{"y" : 349},{"w" : 92},{"h" : 63}]
		}
	],
	"grabAirSpinFinisherLeft1" :
	[
		{
		  "sprite" : [{"x" : 156},{"y" : 345},{"w" : 69},{"h" : 63}]
		},
		{
		  "sprite" : [{"x" : 283},{"y" : 345},{"w" : 85},{"h" : 64}]
		},
		{
		  "sprite" : [{"x" : 453},{"y" : 338},{"w" : 62},{"h" : 63}]
		}	
	],
	"grabAirSpinFinisherLeft2" :
	[
		{
		  "sprite" : [{"x" : 604},{"y" : 335},{"w" : 68},{"h" : 63}]
		}
	],
	"grabAirSpinFinisherLeft3" :
	[
		{
		  "sprite" : [{"x" : 453},{"y" : 338},{"w" : 62},{"h" : 63}]
		},
		{
		  "sprite" : [{"x" : 283},{"y" : 345},{"w" : 85},{"h" : 64}]
		}
	],
	"weaponPipeIdleRight" :
	[
		{
		  "sprite" : [{"x" : 15},{"y" : 457},{"w" : 87},{"h" : 77}]
		}
	],
	"weaponPipeIdleLeft" :
	[
		{
		  "sprite" : [{"x" : 2580},{"y" : 456},{"w" : 105},{"h" : 77}]
		}
	],
	"weaponPipeWalkRight" :
	[
		{
		  "sprite" : [{"x" : 146},{"y" : 456},{"w" : 83},{"h" : 77}]
		},
		{
		  "sprite" : [{"x" : 298},{"y" : 458},{"w" : 88},{"h" : 76}]
		},
		{
		  "sprite" : [{"x" : 458},{"y" : 455},{"w" : 83},{"h" : 77}]
		},
		{
		  "sprite" : [{"x" : 633},{"y" : 461},{"w" : 88},{"h" : 76}]
		}
	],
	"weaponPipeWalkLeft" :
	[
		{
		  "sprite" : [{"x" : 2431},{"y" : 457},{"w" : 108},{"h" : 77}]
		},
		{
		  "sprite" : [{"x" : 2279},{"y" : 459},{"w" : 108},{"h" : 76}]
		},
		{
		  "sprite" : [{"x" : 2119},{"y" : 456},{"w" : 108},{"h" : 77}]
		},
		{
		  "sprite" : [{"x" : 1945},{"y" : 460},{"w" : 108},{"h" : 76}]
		}
	],
	"weaponPipeAttackRight" :
	[
		{
		  "sprite" : [{"x" : 807},{"y" : 453},{"w" : 92},{"h" : 77}]
		},
		{
		  "sprite" : [{"x" : 982},{"y" : 451},{"w" : 134},{"h" : 77}]
		},
		{
		  "sprite" : [{"x" : 807},{"y" : 453},{"w" : 92},{"h" : 77}]
		}
	],
	"weaponPipeAttackLeft" :
	[
		{
		  "sprite" : [{"x" : 1783},{"y" : 462},{"w" : 85},{"h" : 77}]
		},
		{
		  "sprite" : [{"x" : 1604},{"y" : 461},{"w" : 86},{"h" : 77}]
		},
		{
		  "sprite" : [{"x" : 1783},{"y" : 462},{"w" : 85},{"h" : 77}]
		}
	],
	"weaponKnifeIdleRight" :
	[
		{
		  "sprite" : [{"x" : 12},{"y" : 580},{"w" : 97},{"h" : 65}]
		}
	],
	"weaponKnifeIdleLeft" :
	[
		{
		  "sprite" : [{"x" : 2584},{"y" : 579},{"w" : 92},{"h" : 65}]
		}
	],
	"weaponKnifeWalkRight" :
	[
		{
		  "sprite" : [{"x" : 146},{"y" : 575},{"w" : 87},{"h" : 68}]
		},
		{
		  "sprite" : [{"x" : 299},{"y" : 578},{"w" : 88},{"h" : 67}]
		},
		{
		  "sprite" : [{"x" : 454},{"y" : 577},{"w" : 87},{"h" : 68}]
		},
		{
		  "sprite" : [{"x" : 635},{"y" : 580},{"w" : 88},{"h" : 67}]
		}
	],
	"weaponKnifeWalkLeft" :
	[
		{
		  "sprite" : [{"x" : 2431},{"y" : 576},{"w" : 88},{"h" : 68}]
		},
		{
		  "sprite" : [{"x" : 2278},{"y" : 579},{"w" : 90},{"h" : 67}]
		},
		{
		  "sprite" : [{"x" : 2123},{"y" : 578},{"w" : 88},{"h" : 68}]
		},
		{
		  "sprite" : [{"x" : 1945},{"y" : 578},{"w" : 89},{"h" : 67}]
		}
	],
	"weaponKnifeAttackRight" :
	[
		{
		  "sprite" : [{"x" : 956},{"y" : 577},{"w" : 104},{"h" : 63}]
		},
		{
		  "sprite" : [{"x" : 1142},{"y" : 576 },{"w" : 135},{"h" : 63}]
		}
	],
	"weaponKnifeAttackLeft" :
	[
		{
		  "sprite" : [{"x" : 1620},{"y" : 578},{"w" : 85},{"h" : 63}]
		},
		{
		  "sprite" : [{"x" : 1434},{"y" : 577},{"w" : 85},{"h" : 63}]
		}
	],
	"npcGarciaIdleRight" :
	[
		{
		  "sprite" : [{"x" : 61},{"y" : 56},{"w" : 89},{"h" : 63}]
		}
	],
	"npcGarciaIdleLeft" :
	[
		{
		  "sprite" : [{"x" : 2110},{"y" : 57},{"w" : 87},{"h" : 63}]
		}
	],
	"npcGarciaWalkRight" :
	[
		{
		  "sprite" : [{"x" : 219},{"y" : 55},{"w" : 89},{"h" : 63}]
		},
		{
		  "sprite" : [{"x" : 371},{"y" : 56},{"w" : 89},{"h" : 63}]
		},
		{
		  "sprite" : [{"x" : 508},{"y" : 57},{"w" : 89},{"h" : 63}]
		},
		{
		  "sprite" : [{"x" : 654},{"y" : 54},{"w" : 89},{"h" : 63}]
		}
	],
	"npcGarciaWalkLeft" :
	[
		{
		  "sprite" : [{"x" : 1946},{"y" : 55},{"w" : 87},{"h" : 63}]
		},
		{
		  "sprite" : [{"x" : 1794},{"y" : 56},{"w" : 96},{"h" : 63}]
		},
		{
		  "sprite" : [{"x" : 1657},{"y" : 57},{"w" : 87},{"h" : 63}]
		},
		{
		  "sprite" : [{"x" : 1511},{"y" : 54},{"w" : 85},{"h" : 63}]
		}
	],
	"npcGarciaPunchRight1" :
	[
		{
		  "sprite" : [{"x" : 791},{"y" : 62},{"w" : 109},{"h" : 63}]
		}
	],
	"npcGarciaPunchRight2" :
	[
		{
		  "sprite" : [{"x" : 969},{"y" : 64},{"w" : 108},{"h" : 63}]
		}
	],
	"npcGarciaPunchLeft1" :
	[
		{
		  "sprite" : [{"x" : 1374},{"y" : 62},{"w" : 87},{"h" : 63}]
		}
	],
	"npcGarciaPunchLeft2" :
	[
		{
		  "sprite" : [{"x" : 1196},{"y" : 64},{"w" : 97},{"h" : 63}]
		}
	],
	"npcGarciaKnifeIdleRight" :
	[
		{
		  "sprite" : [{"x" : 51},{"y" : 156},{"w" : 84},{"h" : 63}]
		}
	],
	"npcGarciaKnifeIdleLeft" :
	[
		{
		  "sprite" : [{"x" : 2114},{"y" : 156},{"w" : 87},{"h" : 63}]
		}
	],
	"npcGarciaKnifeWalkRight" :
	[
		{
		  "sprite" : [{"x" : 217},{"y" : 160},{"w" : 84},{"h" : 63}]
		},
		{
		  "sprite" : [{"x" : 365},{"y" : 160 },{"w" : 84 },{"h" : 63}]
		},
		{
		  "sprite" : [{"x" : 506},{"y" : 162},{"w" : 84},{"h" : 63}]
		},
		{
		  "sprite" : [{"x" : 652},{"y" : 164},{"w" : 84},{"h" : 63}]
		}
	],
	"npcGarciaKnifeWalkLeft" :
	[
		{
		  "sprite" : [{"x" : 1948},{"y" : 160},{"w" : 88},{"h" : 63}]
		},
		{
		  "sprite" : [{"x" : 1800},{"y" : 160},{"w" : 97},{"h" : 63}]
		},
		{
		  "sprite" : [{"x" : 1659},{"y" : 162},{"w" : 88},{"h" : 63}]
		},
		{
		  "sprite" : [{"x" : 2114},{"y" : 156},{"w" : 87},{"h" : 63}]
		}
	],
	"npcGarciaKnifeAttackRight" :
	[
		{
		  "sprite" : [{"x" : 780},{"y" : 165},{"w" : 118},{"h" : 63}]
		}
	],
	"npcGarciaKnifeAttackLeft" :
	[
		{
		  "sprite" : [{"x" : 1392},{"y" : 165},{"w" : 89},{"h" : 63}]
		}
	],
	"npcPunkyIdleRight" : 
	[
		{
		  "sprite" : [{"x" : 186},{"y" : 389},{"w" : 91},{"h" : 64}]
		}
	],
	"npcPunkyIdleLeft" : 
	[
		{
		  "sprite" : [{"x" : 1980 },{"y" : 389},{"w" : 82},{"h" : 64}]
		}
	],
	"npcPunkyWalkRight" : 
	[
		{
		  "sprite" : [{"x" : 187},{"y" : 389},{"w" : 91},{"h" : 64}]
		},
		{
		  "sprite" : [{"x" : 339},{"y" : 389},{"w" : 92},{"h" : 64}]
		},
		{
		  "sprite" : [{"x" : 480},{"y" : 388},{"w" : 91},{"h" : 64}]
		},
		{
		  "sprite" : [{"x" : 621},{"y" : 389},{"w" : 92},{"h" : 64}]
		}	
	],
	"npcPunkyWalkLeft" : 
	[
		{
		  "sprite" : [{"x" : 1979 },{"y" : 389},{"w" : 82},{"h" : 64}]
		},
		{
		  "sprite" : [{"x" : 1825},{"y" : 389},{"w" : 85},{"h" : 64}]
		},
		{
		  "sprite" : [{"x" : 1684},{"y" : 388},{"w" : 83},{"h" : 64}]
		},
		{
		  "sprite" : [{"x" : 1544},{"y" : 389},{"w" : 78},{"h" : 64}]
		}	
	],
	"npcPunkyGroundAttackRight" :
	[
		{
		  "sprite" : [{"x" : 36},{"y" : 387},{"w" : 88},{"h" : 64}] 
		},
		{
		  "sprite" : [{"x" : 793},{"y" : 379},{"w" : 138},{"h" : 64}] 
		}
	],
	"npcPunkyGroundAttackLeft" :
	[
		{
		  "sprite" : [{"x" : 2129},{"y" : 387},{"w" : 80},{"h" : 64}] 
		},
		{
		  "sprite" : [{"x" : 1372},{"y" : 379},{"w" : 83},{"h" : 64}] 
		}
	],
	"npcNoraIdleRight" : 
	[
		{
		  "sprite" : [{"x" : 172},{"y" : 696},{"w" : 100},{"h" : 68}]
		}
	],
	"npcNoraIdleLeft" : 
	[
		{
		  "sprite" : [{"x" : 1992},{"y" : 696},{"w" : 80},{"h" : 68}]
		}
	],
	"npcNoraWalkRight" :
	[
		{
		  "sprite" : [{"x" : 172},{"y" : 696},{"w" : 100},{"h" : 68}]
		},
		{
		  "sprite" : [{"x" : 324},{"y" : 692},{"w" : 100},{"h" : 69}]
		}
	],
	"npcNoraWalkLeft" :
	[
		{
		  "sprite" : [{"x" : 1992},{"y" : 696},{"w" : 80},{"h" : 68}]
		},
		{
		  "sprite" : [{"x" : 1841},{"y" : 692},{"w" : 85},{"h" : 68}]
		}
	],
	"npcNoraAttackRight" :
	[
		{
		  "sprite" : [{"x" : 500},{"y" : 698},{"w" : 98},{"h" : 68}]
		},
		{
		  "sprite" : [{"x" : 669},{"y" : 693},{"w" : 150},{"h" : 68}]
		},
		{
		  "sprite" : [{"x" : 862},{"y" : 694},{"w" : 140},{"h" : 68}]
		}
	],
	"npcNoraAttackLeft" :
	[
		{
		  "sprite" : [{"x" : 1665},{"y" : 698},{"w" : 96},{"h" : 68}]
		},
		{
		  "sprite" : [{"x" : 1485},{"y" : 693},{"w" : 91},{"h" : 68}]
		},
		{
		  "sprite" : [{"x" : 1292},{"y" : 694},{"w" : 91},{"h" : 68}]
		}
	],
	"npcAntonioIdleRight":
	[
		{
		  "sprite" : [{"x" : 99},{"y" : 921},{"w" : 113},{"h" : 114}]
		}
	],
	"npcAntonioIdleLeft":
	[
		{
		  "sprite" : [{"x" : 2066},{"y" : 921},{"w" : 111},{"h" : 114}]
		}
	],
	"npcAntonioBoomerangIdleRight":
	[
		{
		  "sprite" : [{"x" : 73},{"y" : 1555},{"w" : 113},{"h" : 114}]
		 }
	],
	"npcAntonioBoomerangIdleLeft":
	[
		{
		  "sprite" : [{"x" : 2078},{"y" : 1555},{"w" : 111},{"h" : 114}]
		 }
	],
	"npcAntonioWalkRight" :
	[
		{
		  "sprite" : [{"x" : 99},{"y" : 921},{"w" : 113},{"h" : 114}]
		},
		{
		  "sprite" : [{"x" : 287},{"y" : 924},{"w" : 113},{"h" : 114}]
		},
		{
		  "sprite" : [{"x" : 468},{"y" : 924},{"w" : 113},{"h" : 114}]
		},
		{
		  "sprite" : [{"x" : 677},{"y" : 926},{"w" : 113},{"h" : 114}]
		}
	],
	"npcAntonioWalkLeft" :
	[
		{
		  "sprite" : [{"x" : 2066},{"y" : 921},{"w" : 111},{"h" : 114}]
		},
		{
		  "sprite" : [{"x" : 1878},{"y" : 924},{"w" : 106},{"h" : 114}]
		},
		{
		  "sprite" : [{"x" : 1697},{"y" : 924},{"w" : 106},{"h" : 114}]
		},
		{
		  "sprite" : [{"x" : 1497},{"y" : 927},{"w" : 106},{"h" : 114}]
		}
	],
	"npcAntonioBoomerangWalkRight" :
	[
		{
		  "sprite" : [{"x" : 73},{"y" : 1555},{"w" : 113},{"h" : 114}]
		},
		{
		  "sprite" : [{"x" : 261},{"y" : 1558},{"w" : 113},{"h" : 114}]
		},
		{
		  "sprite" : [{"x" : 442},{"y" : 1558},{"w" : 113},{"h" : 114}]
		},
		{
		  "sprite" : [{"x" : 608},{"y" : 1557},{"w" : 113},{"h" : 114}]
		}
	],
	"npcAntonioBoomerangWalkLeft" :
	[
		{
		  "sprite" : [{"x" : 2078},{"y" : 1555},{"w" : 111},{"h" : 114}]
		},
		{
		  "sprite" : [{"x" : 1890},{"y" : 1558},{"w" : 106},{"h" : 114}]
		},
		{
		  "sprite" : [{"x" : 1709},{"y" : 1558},{"w" : 106},{"h" : 114}]
		},
		{
		  "sprite" : [{"x" : 1543},{"y" : 1557},{"w" : 106},{"h" : 114}]
		}
	],
	"npcAntonioKickRight" :
	[
		{
		  "sprite" : [{"x" : 891},{"y" : 921},{"w" : 92},{"h" : 114}]
		},
		{
		  "sprite" : [{"x" : 868},{"y" : 803},{"w" : 128},{"h" : 114}]
		}
	],
	"npcAntonioKickLeft" :
	[
		{
		  "sprite" : [{"x" : 1290},{"y" : 926},{"w" : 104},{"h" : 114}]
		},
		{
		  "sprite" : [{"x" : 1293},{"y" : 803},{"w" : 87},{"h" : 114}]
		}
	],
	"npcAntonioThrowBoomerangRight":
	[
		{
		  "sprite" : [{"x" : 94},{"y" : 1132},{"w" : 97},{"h" : 114}]
		},
		{
		  "sprite" : [{"x" : 288},{"y" : 1132},{"w" : 113},{"h" : 114}]
		},
		{
		  "sprite" : [{"x" : 99},{"y" : 921},{"w" : 113},{"h" : 114}]
		}
	],
	"npcAntonioThrowBoomerangLeft":
	[
		{
		  "sprite" : [{"x" : 2057},{"y" : 1132},{"w" : 131},{"h" : 114}]
		},
		{
		  "sprite" : [{"x" : 1863},{"y" : 1132},{"w" : 122},{"h" : 114}]
		},
		{
		  "sprite" : [{"x" : 1687},{"y" : 1132},{"w" : 111},{"h" : 114}]
		}
	],
	"npcAntonioRecoverBoomerangRight":
	[
		{
		  "sprite" : [{"x" : 464},{"y" : 1132},{"w" : 93},{"h" : 114}]
		},
		{
		  "sprite" : [{"x" : 288},{"y" : 1132},{"w" : 113},{"h" : 114}]
		},
		{
		  "sprite" : [{"x" : 94},{"y" : 1132},{"w" : 97},{"h" : 114}]
		}
	],
	"npcAntonioRecoverBoomerangLeft":
	[
		{
		  "sprite" : [{"x" : 1687},{"y" : 1132},{"w" : 111},{"h" : 114}]
		},
		{
		  "sprite" : [{"x" : 1863},{"y" : 1132},{"w" : 122},{"h" : 114}]
		},
		{
		  "sprite" : [{"x" : 2057},{"y" : 1132},{"w" : 131},{"h" : 114}]
		}
	],
	"npcItemBoomerangRight" :
	[
		{
		  "sprite" : [{"x" : 49},{"y" : 1361},{"w" : 105},{"h" : 8}]
		},
		{
		  "sprite" : [{"x" : 203},{"y" : 1354},{"w" : 92},{"h" : 18}]
		},
		{
		  "sprite" : [{"x" : 349},{"y" : 1356},{"w" : 105},{"h" : 8}]
		},
		{
		  "sprite" : [{"x" : 503},{"y" : 1354},{"w" : 105},{"h" : 15}]
		}
	],
	"npcBoomerangShadowRight" : 
	[
		{
		  "sprite" : [{"x" : 676},{"y" : 1361},{"w" : 88},{"h" : 4}]
		}
	],	
	"npcItemBoomerangLeft1" :
	[
		{
		  "sprite" : [{"x" : 2102},{"y" : 1361},{"w" : 70},{"h" : 8}]
		},
		{
		  "sprite" : [{"x" : 1948},{"y" : 1354},{"w" : 70},{"h" :15}]
		},
		{
		  "sprite" : [{"x" : 1802},{"y" : 1356},{"w" : 70},{"h" : 9}]
		},
		{
		  "sprite" : [{"x" : 1648},{"y" : 1354},{"w" : 70},{"h" : 15}]
		}
	],
	"npcBoomerangShadowLeft" : 
	[
		{
		  "sprite" : [{"x" : 1480},{"y" : 1361},{"w" : 71},{"h" :4}]
		}
	]
		
}





